dela/__init__.py
dela/__main__.py
dela/file_reader.py
dela/list_comand_config.py
dela/list_command.py
dela/logger.py
dela/todo.py
dela/todo_presentation.py
dela/todo_query.py
dela-0.3.1.dist-info/METADATA
dela-0.3.1.dist-info/WHEEL
dela-0.3.1.dist-info/entry_points.txt
dela-0.3.1.dist-info/RECORD
