Metadata-Version: 2.1
Name: dela
Version: 0.3.1
Summary: 
License: MIT
Author: 'Anton Shuvalov'
Author-email: anton@shuvalov.info
Requires-Python: >=3.8,<4.0
Classifier: License :: OSI Approved :: MIT License
Classifier: Programming Language :: Python :: 3
Classifier: Programming Language :: Python :: 3.8
Classifier: Programming Language :: Python :: 3.9
Classifier: Programming Language :: Python :: 3.10
Classifier: Programming Language :: Python :: 3.11
Classifier: Programming Language :: Python :: 3.12
Requires-Dist: docopt (>=0.6.2,<0.7.0)
Requires-Dist: python-frontmatter (>=1.0.1,<2.0.0)
